[
  {
    "id": "1",
    "name": "Test Angebot 1",
    "description": "Dies ist die Beschreibung für Angebot 1.",
    "price": "258",
    "currency": "EUR",
    "customerId": "4",
    "status": "Active",
    "createdAt": "2025-02-11T20:33:31.949Z",
    "updatedAt": "2025-02-11T20:33:31.949Z"
  },
  {
    "id": "2",
    "name": "Test Angebot 2",
    "description": "Dies ist die Beschreibung für Angebot 2.",
    "price": "557",
    "currency": "EUR",
    "customerId": "1",
    "status": "Active",
    "createdAt": "2025-02-11T20:33:31.949Z",
    "updatedAt": "2025-02-11T20:33:31.949Z"
  },
  {
    "id": "3",
    "name": "Test Angebot 3",
    "description": "Dies ist die Beschreibung für Angebot 3.",
    "price": "182",
    "currency": "EUR",
    "customerId": "2",
    "status": "Draft",
    "createdAt": "2025-02-11T20:33:31.949Z",
    "updatedAt": "2025-02-11T20:33:31.949Z"
  },
  {
    "id": "4",
    "name": "Test Angebot 4",
    "description": "Dies ist die Beschreibung für Angebot 4.",
    "price": "386",
    "currency": "EUR",
    "customerId": "3",
    "status": "Draft",
    "createdAt": "2025-02-11T20:33:31.949Z",
    "updatedAt": "2025-02-11T20:33:31.949Z"
  },
  {
    "id": "5",
    "name": "Test Angebot 5",
    "description": "Dies ist die Beschreibung für Angebot 5.",
    "price": "556",
    "currency": "EUR",
    "customerId": "3",
    "status": "In Progress",
    "createdAt": "2025-02-11T20:33:31.949Z",
    "updatedAt": "2025-02-11T20:33:31.949Z"
  },
  {
    "id": "6",
    "name": "Test Angebot 6",
    "description": "Dies ist die Beschreibung für Angebot 6.",
    "price": "230",
    "currency": "EUR",
    "customerId": "1",
    "status": "Draft",
    "createdAt": "2025-02-11T20:33:31.949Z",
    "updatedAt": "2025-02-11T20:33:31.949Z"
  },
  {
    "id": "7",
    "name": "Test Angebot 7",
    "description": "Dies ist die Beschreibung für Angebot 7.",
    "price": "596",
    "currency": "EUR",
    "customerId": "5",
    "status": "In Progress",
    "createdAt": "2025-02-11T20:33:31.949Z",
    "updatedAt": "2025-02-11T20:33:31.949Z"
  },
  {
    "id": "8",
    "name": "Test Angebot 8",
    "description": "Dies ist die Beschreibung für Angebot 8.",
    "price": "787",
    "currency": "EUR",
    "customerId": "2",
    "status": "In Progress",
    "createdAt": "2025-02-11T20:33:31.949Z",
    "updatedAt": "2025-02-11T20:33:31.949Z"
  },
  {
    "id": "9",
    "name": "Test Angebot 9",
    "description": "Dies ist die Beschreibung für Angebot 9.",
    "price": "146",
    "currency": "EUR",
    "customerId": "2",
    "status": "On Ice",
    "createdAt": "2025-02-11T20:33:31.949Z",
    "updatedAt": "2025-02-11T20:33:31.949Z"
  },
  {
    "id": "10",
    "name": "Test Angebot 10",
    "description": "Dies ist die Beschreibung für Angebot 10.",
    "price": "389",
    "currency": "EUR",
    "customerId": "2",
    "status": "Active",
    "createdAt": "2025-02-11T20:33:31.949Z",
    "updatedAt": "2025-02-11T20:33:31.949Z"
  }
]